collective/__init__.py
collective/directory/__init__.py
collective/directory/configure.zcml
collective/directory/migration.py
collective/directory/profiles.zcml
collective/directory/setuphandlers.py
collective/directory/testing.py
collective/directory/testing.zcml
collective/directory/upgrades.py
collective/directory/vocabulary.py
collective/directory/browser/__init__.py
collective/directory/browser/collective_directory_assign_geolocation.py
collective/directory/browser/collective_directory_export_view.py
collective/directory/browser/collective_directory_import_view.py
collective/directory/browser/configure.zcml
collective/directory/browser/jsonview.py
collective/directory/content/__init__.py
collective/directory/content/card.py
collective/directory/content/category.py
collective/directory/content/configure.zcml
collective/directory/content/directory.py
collective/directory/content/indexers.py
collective/directory/content/templates/detailcard.pt
collective/directory/content/templates/directory.pt
collective/directory/content/templates/listingcards.pt
collective/directory/locales/collective.directory-generated.pot
collective/directory/locales/collective.directory-manual.pot
collective/directory/locales/collective.directory.pot
collective/directory/locales/es/LC_MESSAGES/collective.directory.po
collective/directory/locales/fr/LC_MESSAGES/collective.directory.po
collective/directory/profiles/default/catalog.xml
collective/directory/profiles/default/collective.directory-default.txt
collective/directory/profiles/default/cssregistry.xml
collective/directory/profiles/default/import_steps.xml
collective/directory/profiles/default/jsregistry.xml
collective/directory/profiles/default/metadata.xml
collective/directory/profiles/default/registry.xml
collective/directory/profiles/default/types.xml
collective/directory/profiles/default/types/collective.directory.card.xml
collective.directory-0.2.15.dist-info/DESCRIPTION.rst
collective.directory-0.2.15.dist-info/METADATA
collective.directory-0.2.15.dist-info/RECORD
collective.directory-0.2.15.dist-info/WHEEL
collective.directory-0.2.15.dist-info/metadata.json
collective.directory-0.2.15.dist-info/top_level.txt
