Metadata-Version: 2.0
Name: collective.directory
Version: 0.2.15
Summary: Directory package for Plone
Home-page: https://github.com/imio/
Author: IMIO
Author-email: support@imio.be
License: gpl
Platform: UNKNOWN
Classifier: Environment :: Web Environment
Classifier: Programming Language :: Python
Classifier: Programming Language :: Python :: 2.7
Classifier: Framework :: Plone
Classifier: Framework :: Plone :: 4.2
Classifier: Framework :: Plone :: 4.3
Provides-Extra: test
Requires-Dist: setuptools
Requires-Dist: Plone
Requires-Dist: plone.app.dexterity[grok]
Requires-Dist: plone.api
Requires-Dist: collective.geo.leaflet
Requires-Dist: collective.schedulefield
Requires-Dist: geopy
Provides-Extra: test
Requires-Dist: plone.app.robotframework; extra == 'test'
